spectralcubekit/__init__.py
spectralcubekit/band_parameters.py
spectralcubekit/linear_fitting.py
spectralcubekit/misc_utils.py
spectralcubekit/py.typed
spectralcubekit-0.1.3.dist-info/licenses/LICENSE
spectralcubekit-0.1.3.dist-info/METADATA
spectralcubekit-0.1.3.dist-info/WHEEL
spectralcubekit-0.1.3.dist-info/RECORD
