Metadata-Version: 2.4
Name: spectralcubekit
Version: 0.1.3
Summary: Utility package for working with spectral data cubes.
License: LICENSE
License-File: LICENSE
Keywords: hyperspectral,processing,spectral cube,image
Author: Z.M. Vig
Author-email: zvig@umd.edu
Requires-Python: >=3.13
Classifier: License :: Other/Proprietary License
Classifier: Programming Language :: Python :: 3
Classifier: Programming Language :: Python :: 3.13
Classifier: Programming Language :: Python :: 3.14
Requires-Dist: astropy (>=7.1.0,<8.0.0)
Requires-Dist: numpy (>=2.2,<3.0)
Project-URL: Homepage, https://github.com/z-vig/spectralcubekit.git
Project-URL: Repository, https://github.com/z-vig/spectralcubekit.git
